sbom4rpms/command.py
sbom4rpms/consts.py
sbom4rpms/gitinspect.py
sbom4rpms/main.py
sbom4rpms/model.py
sbom4rpms/rpminspect.py
sbom4rpms/sbom/generator.py
sbom4rpms/sbom/cyclonedx/model.py
sbom4rpms/sbom/lib/purl.py
sbom4rpms/sbom/spdx/document-gitsubmodules.tmpl
sbom4rpms/sbom/spdx/document-header.tmpl
sbom4rpms/sbom/spdx/document-package.tmpl
sbom4rpms/sbom/spdx/document.tmpl
sbom4rpms/sbom/spdx/model.py
sbom4rpms-0.0.2.dist-info/LICENSE
sbom4rpms-0.0.2.dist-info/METADATA
sbom4rpms-0.0.2.dist-info/WHEEL
sbom4rpms-0.0.2.dist-info/entry_points.txt
sbom4rpms-0.0.2.dist-info/top_level.txt
sbom4rpms-0.0.2.dist-info/RECORD
