Metadata-Version: 2.1
Name: sbom4rpms
Version: 0.0.2
Author-email: Michael Engel <mengel@redhat.com>
Maintainer-email: Michael Engel <mengel@redhat.com>
Project-URL: Homepage, https://github.com/engelmi/sbom-for-rpms
Project-URL: Documentation, https://github.com/engelmi/sbom-for-https://github.com/engelmi/sbom4rpm/issues
Project-URL: Repository, https://github.com/engelmi/sbom4rpm.git
Project-URL: Issues, https://github.com/engelmi/sbom4rpm/issues
Keywords: SBOM,RPM,Generation
Classifier: Programming Language :: Python
Classifier: Programming Language :: Python :: 3
Requires-Python: >=3.9
License-File: LICENSE
Requires-Dist: Jinja2 >=3.1.2
